siebanxico/__init__.py
siebanxico/siebanxico.py
Banxico_SIE-1.0.0.dist-info/LICENSE
Banxico_SIE-1.0.0.dist-info/METADATA
Banxico_SIE-1.0.0.dist-info/WHEEL
Banxico_SIE-1.0.0.dist-info/top_level.txt
Banxico_SIE-1.0.0.dist-info/RECORD
