Metadata-Version: 2.1
Name: Banxico-SIE
Version: 1.0.0
Summary: This packages enables downloading economic and financial time series hosted on Banco de Mexico's Sistema de Informacion Economica (SIE) directly as a time-indexed Pandas DataFrame. Time series metadata is available on English and Spanish.
Author-email: Ezequiel Piedras Romero <epiedrasr@banxico.org.mx>
License: MIT License
Project-URL: Homepage, https://github.com/chekecocol/siebanxico
Keywords: Banco de Mexico,Banxico,Sistema de Informacion Economica,SIE,economic time series,economic data,financial time series
Classifier: License :: OSI Approved :: MIT License
Classifier: Programming Language :: Python
Classifier: Programming Language :: Python :: 3
Requires-Python: >=3.6
License-File: LICENSE
Requires-Dist: requests
Requires-Dist: pandas >=1.4.2
